amarillo/__init__.py
amarillo/plugins/__init__.py
amarillo/plugins/gtfs_exporter/__init__.py
amarillo/plugins/gtfs_exporter/config.py
amarillo/plugins/gtfs_exporter/router.py
amarillo_gtfs_exporter-2.0.5.dist-info/LICENSE
amarillo_gtfs_exporter-2.0.5.dist-info/METADATA
amarillo_gtfs_exporter-2.0.5.dist-info/WHEEL
amarillo_gtfs_exporter-2.0.5.dist-info/top_level.txt
amarillo_gtfs_exporter-2.0.5.dist-info/RECORD
