Metadata-Version: 2.2
Name: amarillo-gtfs-exporter
Version: 2.0.5
Summary: GTFS export plugin for Amarillo
License:                     GNU AFFERO GENERAL PUBLIC LICENSE
License-File: LICENSE
Requires-Dist: amarillo
